LICENSE
README.md
RNAKit.py
RNAport.py
setup.py
test.sh
RNAport.egg-info/PKG-INFO
RNAport.egg-info/SOURCES.txt
RNAport.egg-info/dependency_links.txt
RNAport.egg-info/entry_points.txt
RNAport.egg-info/not-zip-safe
RNAport.egg-info/requires.txt
RNAport.egg-info/top_level.txt
__pycache__/RNAKit.cpython-36.pyc
example/Ntangutorum_transome.xlsx
example/bms.txt
example/denovo.conf
example/input.PE.conf
example/input.config.txt
example/prepare.sh
example/rawdata.list
readProject/Forxlsx.py
readProject/__init__.py
readProject/bk.Forxlsx.py
readProject/rawData.py
utils/bk.findFile.py
utils/findFile.py
utils/runscanDir.py
utils/test.py
utils/test.txt
utils/testWalk.py
utils/testindex.txt